gpframe/__init__.py
gpframe/exceptions.py
gpframe/_impl/__init__.py
gpframe/_impl/common.py
gpframe/_impl/context.py
gpframe/_impl/phase.py
gpframe/_impl/protocols.py
gpframe/_impl/frame/__init__.py
gpframe/_impl/frame/circuit.py
gpframe/_impl/frame/frame_base.py
gpframe/_impl/frame/future.py
gpframe/_impl/frame/root.py
gpframe/_impl/frame/root_base.py
gpframe/_impl/frame/root_ipc.py
gpframe/_impl/frame/sub.py
gpframe/_impl/frame/sub_ipc.py
gpframe/_impl/handler/__init__.py
gpframe/_impl/handler/event.py
gpframe/_impl/handler/exception.py
gpframe/_impl/handler/redo.py
gpframe/_impl/message/__init__.py
gpframe/_impl/message/message.py
gpframe/_impl/message/reflector.py
gpframe/_impl/routine/__init__.py
gpframe/_impl/routine/asynchronous.py
gpframe/_impl/routine/base.py
gpframe/_impl/routine/result.py
gpframe/_impl/routine/subprocess.py
gpframe/_impl/routine/synchronous.py
gpframe/contracts/__init__.py
gpframe/contracts/exceptions.py
gpframe/contracts/protocols.py
gpframe/gproot/__init__.py
gpframe/gproot/event.py
gpframe/gproot/routine.py
gpframe/gproot/ipc/__init__.py
gpframe/gproot/ipc/event.py
gpframe/gproot/ipc/routine.py
gpframe/gpsub/__init__.py
gpframe/gpsub/event.py
gpframe/gpsub/routine.py
gpframe/gpsub/ipc/__init__.py
gpframe/gpsub/ipc/event.py
gpframe/gpsub/ipc/routine.py
gpframe-0.0.34.dist-info/licenses/LICENSE
gpframe-0.0.34.dist-info/METADATA
gpframe-0.0.34.dist-info/WHEEL
gpframe-0.0.34.dist-info/top_level.txt
gpframe-0.0.34.dist-info/RECORD
