Metadata-Version: 2.4
Name: gpframe
Version: 0.0.34
Summary: A general-purpose framework for routine execution with concurrency and event handling.
Author: minoru_jp
License: MIT License
Project-URL: Homepage, https://github.com/minoru-jp/gpframe
Project-URL: Source, https://github.com/minoru-jp/gpframe
Project-URL: Issues, https://github.com/minoru-jp/gpframe/issues
Keywords: general-purpose,framework,concurrency,async,subprocess,event,lifecycle,context,wrapper,skeleton,workflow,execution
Classifier: Programming Language :: Python :: 3
Classifier: License :: OSI Approved :: MIT License
Classifier: Development Status :: 3 - Alpha
Classifier: Intended Audience :: Developers
Classifier: Topic :: Software Development :: Libraries :: Python Modules
Requires-Python: >=3.10
License-File: LICENSE
Dynamic: license-file
